nonebot_plugin_hypixel/__init__.py
nonebot_plugin_hypixel/api_handle.py
nonebot_plugin_hypixel/config.py
nonebot_plugin_hypixel/request.py
nonebot_plugin_hypixel-1.0.1.dist-info/LICENSE.txt
nonebot_plugin_hypixel-1.0.1.dist-info/METADATA
nonebot_plugin_hypixel-1.0.1.dist-info/WHEEL
nonebot_plugin_hypixel-1.0.1.dist-info/top_level.txt
nonebot_plugin_hypixel-1.0.1.dist-info/RECORD
