Metadata-Version: 2.1
Name: nonebot-plugin-hypixel
Version: 1.0.1
Summary: 基于OneBot适配器的NoneBot2获取Mineceaft最大的小游戏服务器Hypixel的玩家数据的插件
Home-page: https://github.com/SkyDynamic/nonebot_plugin_hypixel
Author: Sky_Dynamic
Author-email: SkyDynamic@outlook.com
Keywords: pip,nonebot2,nonebot,nonebot_plugin,hypixel
Platform: any
Classifier: Programming Language :: Python :: 3
Classifier: License :: OSI Approved :: MIT License
Classifier: Operating System :: OS Independent
Requires-Python: >=3.7.3
License-File: LICENSE.txt
Requires-Dist: nonebot2 (>=2.0.0rc1)
Requires-Dist: nonebot-adapter-onebot (>=2.1.5)
Requires-Dist: httpx (>=0.23.1)
Requires-Dist: requests (>=2.25.1)
